BianchengSuixiangBokeNimingShuWenji20092015/README.md
BianchengSuixiangBokeNimingShuWenji20092015/__init__.py
BianchengSuixiangBokeNimingShuWenji20092015/__main__.py
BianchengSuixiangBokeNimingShuWenji20092015/file.epub
BianchengSuixiangBokeNimingShuWenji20092015/index.html
BianchengSuixiangBokeNimingShuWenji20092015/css/__init__.py
BianchengSuixiangBokeNimingShuWenji20092015/css/annotations.css
BianchengSuixiangBokeNimingShuWenji20092015/css/main.css
BianchengSuixiangBokeNimingShuWenji20092015/css/normalize.css
BianchengSuixiangBokeNimingShuWenji20092015/css/popup.css
BianchengSuixiangBokeNimingShuWenji20092015/font/__init__.py
BianchengSuixiangBokeNimingShuWenji20092015/font/fontello.eot
BianchengSuixiangBokeNimingShuWenji20092015/font/fontello.svg
BianchengSuixiangBokeNimingShuWenji20092015/font/fontello.ttf
BianchengSuixiangBokeNimingShuWenji20092015/font/fontello.woff
BianchengSuixiangBokeNimingShuWenji20092015/img/__init__.py
BianchengSuixiangBokeNimingShuWenji20092015/img/annotator-glyph-sprite.png
BianchengSuixiangBokeNimingShuWenji20092015/img/annotator-icon-sprite.png
BianchengSuixiangBokeNimingShuWenji20092015/img/apple-touch-icon.png
BianchengSuixiangBokeNimingShuWenji20092015/img/cancelfullscreen.png
BianchengSuixiangBokeNimingShuWenji20092015/img/close.png
BianchengSuixiangBokeNimingShuWenji20092015/img/fullscreen.png
BianchengSuixiangBokeNimingShuWenji20092015/img/loader.gif
BianchengSuixiangBokeNimingShuWenji20092015/img/menu-icon.png
BianchengSuixiangBokeNimingShuWenji20092015/img/save.png
BianchengSuixiangBokeNimingShuWenji20092015/img/saved.png
BianchengSuixiangBokeNimingShuWenji20092015/img/settings-s.png
BianchengSuixiangBokeNimingShuWenji20092015/img/settings.png
BianchengSuixiangBokeNimingShuWenji20092015/img/star.png
BianchengSuixiangBokeNimingShuWenji20092015/js/__init__.py
BianchengSuixiangBokeNimingShuWenji20092015/js/epub.js
BianchengSuixiangBokeNimingShuWenji20092015/js/epub.min.js
biancheng_suixiang_boke_niming_shu_wenji_2009_2015-2024.3.2.0.dist-info/METADATA
biancheng_suixiang_boke_niming_shu_wenji_2009_2015-2024.3.2.0.dist-info/WHEEL
biancheng_suixiang_boke_niming_shu_wenji_2009_2015-2024.3.2.0.dist-info/entry_points.txt
biancheng_suixiang_boke_niming_shu_wenji_2009_2015-2024.3.2.0.dist-info/top_level.txt
biancheng_suixiang_boke_niming_shu_wenji_2009_2015-2024.3.2.0.dist-info/RECORD
